<annotation>
    <folder>images</folder>
    <filename>00084_road591.png</filename>
    <size>
        <width>300</width>
        <height>400</height>
        <depth>3</depth>
    </size>
    <segmented>0</segmented>
    <object>
        <name>speedlimit</name>
        <pose>Unspecified</pose>
        <truncated>0</truncated>
        <occluded>0</occluded>
        <difficult>0</difficult>
        <bndbox>
            <xmin>10</xmin>
            <ymin>200</ymin>
            <xmax>56</xmax>
            <ymax>246</ymax>
        </bndbox>
    </object>
</annotation>